streamlit_vega_lite/__init__.py
streamlit_vega_lite/frontend/build/asset-manifest.json
streamlit_vega_lite/frontend/build/index.html
streamlit_vega_lite/frontend/build/precache-manifest.7344f18f46a6e54b3fb79e4365698f39.js
streamlit_vega_lite/frontend/build/service-worker.js
streamlit_vega_lite/frontend/build/static/css/2.ae9f1eb3.chunk.css
streamlit_vega_lite/frontend/build/static/css/2.ae9f1eb3.chunk.css.map
streamlit_vega_lite/frontend/build/static/css/2.d9ad5f5c.chunk.css
streamlit_vega_lite/frontend/build/static/css/2.d9ad5f5c.chunk.css.map
streamlit_vega_lite/frontend/build/static/js/2.12eee45d.chunk.js
streamlit_vega_lite/frontend/build/static/js/2.12eee45d.chunk.js.LICENSE.txt
streamlit_vega_lite/frontend/build/static/js/2.12eee45d.chunk.js.map
streamlit_vega_lite/frontend/build/static/js/2.71e03640.chunk.js
streamlit_vega_lite/frontend/build/static/js/2.71e03640.chunk.js.LICENSE.txt
streamlit_vega_lite/frontend/build/static/js/2.71e03640.chunk.js.map
streamlit_vega_lite/frontend/build/static/js/main.3d96c73f.chunk.js
streamlit_vega_lite/frontend/build/static/js/main.3d96c73f.chunk.js.map
streamlit_vega_lite/frontend/build/static/js/main.ad22acb0.chunk.js
streamlit_vega_lite/frontend/build/static/js/main.ad22acb0.chunk.js.map
streamlit_vega_lite/frontend/build/static/js/runtime-main.2c4fad4e.js
streamlit_vega_lite/frontend/build/static/js/runtime-main.2c4fad4e.js.map
streamlit_vega_lite/frontend/build/static/js/runtime-main.5e376684.js
streamlit_vega_lite/frontend/build/static/js/runtime-main.5e376684.js.map
streamlit_vega_lite-0.1.0.dist-info/LICENSE
streamlit_vega_lite-0.1.0.dist-info/METADATA
streamlit_vega_lite-0.1.0.dist-info/WHEEL
streamlit_vega_lite-0.1.0.dist-info/top_level.txt
streamlit_vega_lite-0.1.0.dist-info/RECORD
