Metadata-Version: 2.1
Name: streamlit-vega-lite
Version: 0.1.0
Summary: A Vega-Lite Component for Streamlit that Supports Selections
Home-page: https://github.com/domoritz/streamlit-vega-lite
Author: Dominik Moritz, Cameron Yick
Author-email: 
License: UNKNOWN
Platform: UNKNOWN
Requires-Python: >=3.6
